edc_screening/__init__.py
edc_screening/age_evaluator.py
edc_screening/apps.py
edc_screening/auth_objects.py
edc_screening/auths.py
edc_screening/choices.py
edc_screening/constants.py
edc_screening/eligibility.py
edc_screening/exceptions.py
edc_screening/fc.py
edc_screening/form_validator_mixins.py
edc_screening/gender_evaluator.py
edc_screening/modelform_mixins.py
edc_screening/models.py
edc_screening/screening_eligibility.py
edc_screening/screening_identifier.py
edc_screening/stubs.py
edc_screening/utils.py
edc_screening/migrations/0001_initial.py
edc_screening/migrations/0002_alter_edcpermissions_device_created_and_more.py
edc_screening/migrations/0003_alter_edcpermissions_options_and_more.py
edc_screening/migrations/__init__.py
edc_screening/model_mixins/__init__.py
edc_screening/model_mixins/eligibility_model_mixin.py
edc_screening/model_mixins/screening_fields_model_mixin.py
edc_screening/model_mixins/screening_identifier_model_mixin.py
edc_screening/model_mixins/screening_methods_model_mixin.py
edc_screening/model_mixins/screening_model_mixin.py
edc_screening/tests/__init__.py
edc_screening/tests/test_evaluators.py
edc_screening/tests/test_screening.py
edc_screening/tests/test_screening_eligibility.py
edc_screening/tests/test_settings.py
edc_screening/tests/urls.py
edc_screening/tests/etc/user-aes-local.key
edc_screening/tests/etc/user-aes-restricted.key
edc_screening/tests/etc/user-rsa-local-private.pem
edc_screening/tests/etc/user-rsa-local-public.pem
edc_screening/tests/etc/user-rsa-restricted-private.pem
edc_screening/tests/etc/user-rsa-restricted-public.pem
edc_screening/tests/etc/user-salt-local.key
edc_screening/tests/etc/user-salt-restricted.key
edc_screening-1.1.0.dist-info/licenses/AUTHORS
edc_screening-1.1.0.dist-info/licenses/LICENSE
screening_app/__init__.py
screening_app/apps.py
screening_app/consents.py
screening_app/eligibility.py
screening_app/models.py
edc_screening-1.1.0.dist-info/METADATA
edc_screening-1.1.0.dist-info/WHEEL
edc_screening-1.1.0.dist-info/top_level.txt
edc_screening-1.1.0.dist-info/RECORD
